riscv_isac/InstructionObject.py
riscv_isac/__init__.py
riscv_isac/cgf_normalize.py
riscv_isac/constants.py
riscv_isac/coverage.py
riscv_isac/fp_dataset.py
riscv_isac/isac.py
riscv_isac/log.py
riscv_isac/main.py
riscv_isac/requirements.txt
riscv_isac/utils.py
riscv_isac/data/__init__.py
riscv_isac/data/constants.py
riscv_isac/data/rvopcodesdecoder.py
riscv_isac/plugins/__init__.py
riscv_isac/plugins/c_sail.py
riscv_isac/plugins/internaldecoder.py
riscv_isac/plugins/specification.py
riscv_isac/plugins/spike.py
tests/__init__.py
tests/test_riscv_isac.py
riscv_isac-0.18.0.dist-info/LICENSE.incore
riscv_isac-0.18.0.dist-info/METADATA
riscv_isac-0.18.0.dist-info/WHEEL
riscv_isac-0.18.0.dist-info/entry_points.txt
riscv_isac-0.18.0.dist-info/top_level.txt
riscv_isac-0.18.0.dist-info/RECORD
