Metadata-Version: 1.2
Name: riscv-isac
Version: 0.18.0
Summary: RISC-V ISAC
Home-page: https://github.com/riscv/riscv-isac
Author: InCore Semiconductors Pvt. Ltd.
Author-email: info@incoresemi.com
License: BSD-3-Clause
Keywords: riscv_isac
Platform: UNKNOWN
Classifier: Programming Language :: Python :: 3.6
Classifier: License :: OSI Approved :: BSD License
Classifier: Development Status :: 4 - Beta
Requires-Python: >=3.6.0
